konfig/__init__.py
konfig/parser.py
konfig/version.py
konfig_parser-0.0.2.dist-info/METADATA
konfig_parser-0.0.2.dist-info/WHEEL
konfig_parser-0.0.2.dist-info/top_level.txt
konfig_parser-0.0.2.dist-info/RECORD
