Metadata-Version: 2.1
Name: konfig-parser
Version: 0.0.2
Summary: Configuration parser purpose built to be simple
Home-page: https://github.com/Kryptos-Team/config-parser.git
Author: Abhimanyu Saharan
Author-email: desk.abhimanyu@gmail.com
License: MIT
Keywords: stratum,mining,kryptos
Platform: UNKNOWN
Classifier: Development Status :: 3 - Alpha
Classifier: Intended Audience :: Developers
Classifier: License :: OSI Approved :: MIT License
Classifier: Natural Language :: English
Classifier: Operating System :: OS Independent
Classifier: Programming Language :: Python :: 3.6
Classifier: Programming Language :: Python :: 3.7
Classifier: Programming Language :: Python :: 3.8
Classifier: Programming Language :: Python :: 3.9
Requires-Dist: pyyaml
